chill_coffee_cash/__init__.py
chill_coffee_cash/main.py
chill_coffee_cash-0.1.0.dist-info/LICENSE
chill_coffee_cash-0.1.0.dist-info/METADATA
chill_coffee_cash-0.1.0.dist-info/WHEEL
chill_coffee_cash-0.1.0.dist-info/entry_points.txt
chill_coffee_cash-0.1.0.dist-info/top_level.txt
chill_coffee_cash-0.1.0.dist-info/RECORD
