Metadata-Version: 2.1
Name: chill-coffee-cash
Version: 0.1.0
Summary: A cash register system for coffee shop
Author: quzaory
Author-email: zHIjsBlKlHF7oCZ@proton.me
Classifier: Programming Language :: Python :: 3
Classifier: License :: OSI Approved :: MIT License
Classifier: Operating System :: OS Independent
Requires-Python: >=3.7
License-File: LICENSE
Requires-Dist: PySide6>=6.5.0
